ixc_utils/__init__.py
ixc_utils/api.py
ixc_utils/data.py
ixc_utils/filters.py
ixc_utils/text.py
ixc_utils-0.2.1.dist-info/licenses/LICENSE
ixc_utils-0.2.1.dist-info/METADATA
ixc_utils-0.2.1.dist-info/WHEEL
ixc_utils-0.2.1.dist-info/top_level.txt
ixc_utils-0.2.1.dist-info/RECORD
