Metadata-Version: 2.4
Name: ixc-utils
Version: 0.2.1
Summary: Funções utilitárias para trabalhar com API IXC e manipulação de dados
Author-email: César Bragança <cesarbgf.contato@gmail.com>
Project-URL: Homepage, https://github.com/cesarbgf/ixc-utils
Project-URL: Issues, https://github.com/cesarbgf/ixc-utils/issues
Project-URL: Repository, https://github.com/cesarbgf/ixc-utils
Keywords: ixc,api,utils,isp,telecom
Classifier: Programming Language :: Python :: 3
Classifier: Programming Language :: Python :: 3.8
Classifier: Programming Language :: Python :: 3.9
Classifier: Programming Language :: Python :: 3.10
Classifier: Programming Language :: Python :: 3.11
Classifier: Programming Language :: Python :: 3.12
Classifier: License :: OSI Approved :: MIT License
Classifier: Operating System :: OS Independent
Classifier: Development Status :: 4 - Beta
Classifier: Intended Audience :: Developers
Classifier: Topic :: Software Development :: Libraries :: Python Modules
Requires-Python: >=3.8
Requires-Dist: requests>=2.28.0
Requires-Dist: pandas>=1.5.0
Requires-Dist: numpy>=1.23.0
Provides-Extra: dev
Requires-Dist: pytest>=7.0.0; extra == "dev"
Requires-Dist: black>=22.0.0; extra == "dev"
Requires-Dist: flake8>=5.0.0; extra == "dev"
